hachitool-1.0.2.dist-info/METADATA
hachitool-1.0.2.dist-info/WHEEL
hachitool-1.0.2.dist-info/entry_points.txt
hachitool-1.0.2.dist-info/licenses/LICENSE.md
hachitool/__init__.py
hachitool/commands.py
hachitool/commands.pyi
hachitool/file_ops.py
hachitool/file_ops.pyi
hachitool-1.0.2.dist-info/RECORD
