Metadata-Version: 2.1
Name: hachitool
Version: 1.0.2
Summary: Utilities for working with Python scripts in GitHub Actions
Author-Email: celsius narhwal <hello@celsiusnarhwal.dev>
Project-URL: Repository, https://github.com/celsiusnarhwal/hachitool
Project-URL: Issues, https://github.com/celsiusnarhwal/hachitool/issues
Project-URL: Changelog, https://github.com/celsiusnarhwal/hachitool/blob/main/CHANGELOG.md
Requires-Python: >=3.11
Requires-Dist: multimethod>=1.12
Requires-Dist: pydantic>=2.10.3
